mawo/__init__.py
mawo/document.py
mawo/russian.py
mawo/vocab.py
mawo_core-0.1.2.dist-info/licenses/LICENSE
mawo_core-0.1.2.dist-info/METADATA
mawo_core-0.1.2.dist-info/WHEEL
mawo_core-0.1.2.dist-info/top_level.txt
mawo_core-0.1.2.dist-info/RECORD
