Metadata-Version: 2.4
Name: mawo-core
Version: 0.1.2
Summary: Unified API for Russian NLP - combines razdel, pymorphy3, slovnet, natasha
Author-email: MAWO Team <info@mawo.ru>
License-Expression: MIT
Project-URL: Homepage, https://github.com/mawo-ru/mawo-core
Project-URL: Repository, https://github.com/mawo-ru/mawo-core
Project-URL: Issues, https://github.com/mawo-ru/mawo-core/issues
Keywords: nlp,russian,morphology,ner,tokenization,unified-api
Classifier: Development Status :: 3 - Alpha
Classifier: Intended Audience :: Developers
Classifier: Programming Language :: Python :: 3
Classifier: Programming Language :: Python :: 3.10
Classifier: Programming Language :: Python :: 3.11
Classifier: Programming Language :: Python :: 3.12
Classifier: Programming Language :: Python :: 3.13
Classifier: Topic :: Text Processing :: Linguistic
Requires-Python: >=3.10
License-File: LICENSE
Requires-Dist: mawo-pymorphy3>=1.0.4
Requires-Dist: mawo-razdel>=1.0.6
Requires-Dist: mawo-grammar>=0.2.1
Provides-Extra: all
Requires-Dist: mawo-slovnet>=1.0.7; extra == "all"
Requires-Dist: mawo-natasha>=1.0.3; extra == "all"
Provides-Extra: dev
Requires-Dist: pytest>=9.0.0; extra == "dev"
Requires-Dist: pytest-cov>=7.0.0; extra == "dev"
Requires-Dist: black>=25.11.0; extra == "dev"
Requires-Dist: ruff>=0.14.4; extra == "dev"
Requires-Dist: mypy>=1.18.2; extra == "dev"
Dynamic: license-file
